roulette/__init__.py
roulette/__main__.py
roulette/play.py
roulette/utils/__init__.py
roulette/utils/config.py
roulette/vars/__init__.py
roulette/vars/bets.py
roulette/vars/numbers.py
roulette-1.5.dist-info/LICENSE
roulette-1.5.dist-info/METADATA
roulette-1.5.dist-info/WHEEL
roulette-1.5.dist-info/entry_points.txt
roulette-1.5.dist-info/top_level.txt
roulette-1.5.dist-info/RECORD
