Metadata-Version: 2.1
Name: roulette
Version: 1.5
Summary: Roullette game
Home-page: https://github.com/gabfl/roulette
Author: Gabriel Bordeaux
Author-email: pypi@gab.lc
License: MIT
Platform: UNKNOWN
Classifier: Topic :: Games/Entertainment :: Simulation
Classifier: License :: OSI Approved :: MIT License
Classifier: Operating System :: MacOS
Classifier: Operating System :: POSIX :: Linux
Classifier: Natural Language :: English
Classifier: Programming Language :: Python :: 3
Classifier: Programming Language :: Python
Classifier: Development Status :: 4 - Beta
Requires-Dist: argparse
Requires-Dist: configparser
Requires-Dist: tabulate
